aot_client/__init__.py
aot_client/client.py
aot_client/filters.py
aot_client/responses.py
aot_client-2.1.0.dist-info/LICENSE
aot_client-2.1.0.dist-info/METADATA
aot_client-2.1.0.dist-info/WHEEL
aot_client-2.1.0.dist-info/top_level.txt
aot_client-2.1.0.dist-info/RECORD
