Metadata-Version: 2.1
Name: aot-client
Version: 2.1.0
Summary: The Official Python Client of the Array of Things API
Home-page: https://github.com/UrbanCCD-UChicago/aot-client-py
Author: Vince Forgione
Author-email: vforgione@uchicago.edu
License: MIT
Platform: UNKNOWN
Classifier: Development Status :: 5 - Production/Stable
Classifier: Intended Audience :: Developers
Classifier: License :: OSI Approved :: MIT License
Classifier: Environment :: Console
Classifier: Environment :: Web Environment
Classifier: Intended Audience :: Developers
Classifier: Intended Audience :: Information Technology
Classifier: Intended Audience :: System Administrators
Classifier: Natural Language :: English
Classifier: Operating System :: OS Independent
Classifier: Programming Language :: Python :: 3.6
Requires-Dist: requests
